containerops/__init__.py
containerops/_ipam.py
containerops/_port_alloc.py
containerops/knot.py
containerops/nebula.py
containerops/podman.py
container_ops-0.1.0.dist-info/METADATA
container_ops-0.1.0.dist-info/WHEEL
container_ops-0.1.0.dist-info/top_level.txt
container_ops-0.1.0.dist-info/RECORD
