Metadata-Version: 2.4
Name: container-ops
Version: 0.1.0
Summary: Add your description here
Requires-Python: >=3.13
Requires-Dist: pyinfra>=3.2
